ligo_proxy_utils/__init__.py
ligo_proxy_utils/ligo_proxy_init.py
ligo_proxy_utils/tests/__init__.py
ligo_proxy_utils/tests/test_ligo_proxy_init.py
ligo_proxy_utils-2.0.2.dist-info/METADATA
ligo_proxy_utils-2.0.2.dist-info/WHEEL
ligo_proxy_utils-2.0.2.dist-info/entry_points.txt
ligo_proxy_utils-2.0.2.dist-info/top_level.txt
ligo_proxy_utils-2.0.2.dist-info/RECORD
