Metadata-Version: 2.2
Name: ligo-proxy-utils
Version: 2.0.2
Summary: Utilties for obtaining short-lived credentials for LIGO
Author-email: Duncan Macleod <duncan.macleod@ligo.org>
License: GPL-3.0-or-later
Project-URL: Homepage, https://git.ligo.org/computing/iam/ligo-proxy-utils
Project-URL: Bug Tracker, https://git.ligo.org/computing/iam/ligo-proxy-utils/-/issues
Project-URL: Documentation, https://rtd.igwn.org/projects/ligo-proxy-utils
Classifier: Development Status :: 5 - Production/Stable
Classifier: Intended Audience :: System Administrators
Classifier: License :: OSI Approved :: GNU General Public License v3 or later (GPLv3+)
Classifier: Operating System :: OS Independent
Classifier: Programming Language :: Python :: 3
Classifier: Programming Language :: Python :: 3.6
Classifier: Programming Language :: Python :: 3.7
Classifier: Programming Language :: Python :: 3.8
Classifier: Programming Language :: Python :: 3.9
Classifier: Programming Language :: Python :: 3.10
Classifier: Programming Language :: Python :: 3.11
Classifier: Programming Language :: Python :: 3.12
Classifier: Topic :: Scientific/Engineering :: Astronomy
Classifier: Topic :: Scientific/Engineering :: Physics
Requires-Python: >=3.6
Requires-Dist: ciecplib
Provides-Extra: docs
Requires-Dist: furo>=2024.5.6; extra == "docs"
Requires-Dist: sphinx>=7.3.7; extra == "docs"
Requires-Dist: sphinx-argparse>=0.4.0; extra == "docs"
Requires-Dist: sphinx-copybutton>=0.5.2; extra == "docs"
Requires-Dist: sphinx-inline-tabs>=2023.4.21; extra == "docs"
Provides-Extra: test
Requires-Dist: pytest; extra == "test"
